LICENSE
README.md
setup.py
truckersfm/__init__.py
truckersfm/base.py
truckersfm/baseExceptions.py
truckersfm.py.egg-info/PKG-INFO
truckersfm.py.egg-info/SOURCES.txt
truckersfm.py.egg-info/dependency_links.txt
truckersfm.py.egg-info/requires.txt
truckersfm.py.egg-info/top_level.txt