Metadata-Version: 2.1
Name: truckersfm.py
Version: 1.0.0.0
Summary: Simple API Wrapper for the TruckersFM API
Home-page: https://github.com/mrbean565/TruckersFM.py
Author: Bean
Author-email: bean@truckerbean.com
License: GNU
Keywords: api wrapper truckersfm
Platform: UNKNOWN
Classifier: Programming Language :: Python :: 3
Classifier: License :: OSI Approved :: GNU General Public License v3 or later (GPLv3+)
Classifier: Operating System :: OS Independent
Requires-Python: >=3.7
License-File: LICENSE
